gym_kiloBot/__init__.py
gym_kiloBot/envs/__init__.py
gym_kiloBot/envs/action.py
gym_kiloBot/envs/arrow.py
gym_kiloBot/envs/kiloBot.py
gym_kiloBot/envs/kilobot_env.py
gym_kiloBot-0.0.2.dist-info/METADATA
gym_kiloBot-0.0.2.dist-info/WHEEL
gym_kiloBot-0.0.2.dist-info/top_level.txt
gym_kiloBot-0.0.2.dist-info/RECORD
