Metadata-Version: 2.1
Name: gym-kiloBot
Version: 0.0.2
Summary: An OpenAI Gym env for a swarm of kilo bots which have a limited perception of the world
Home-page: UNKNOWN
Author: UNKNOWN
Author-email: UNKNOWN
License: UNKNOWN
Platform: UNKNOWN
